MANIFEST.in
README
setup.py
progtools/__init__.py
progtools/command.py
progtools/errors.py
progtools/path.py
progtools/program.py
progtools.egg-info/PKG-INFO
progtools.egg-info/SOURCES.txt
progtools.egg-info/dependency_links.txt
progtools.egg-info/top_level.txt
progtools.egg-info/zip-safe