Metadata-Version: 1.0
Name: progtools
Version: 0.2.2
Summary: progtools is a simple command-line interface (CLI) library for Python.
Home-page: http://launchpad.net/progtools
Author: Ross Light
Author-email: rlight2@gmail.com
License: MIT
Download-URL: https://launchpad.net/progtools/+download
Keywords: cli,library,command,line,text
Platform: UNKNOWN
Classifier: Development Status :: 3 - Alpha
Classifier: Intended Audience :: Developers
Classifier: License :: OSI Approved :: MIT License
Classifier: Operating System :: OS Independent
Classifier: Programming Language :: Python
Classifier: Topic :: Software Development :: Libraries :: Python Modules
